<?xml version="1.0" encoding="utf-8" ?>
<dwsync>
<file name="edita_categoria.php" server="C:/Program Files/Apache Software Foundation/Apache2.2/htdocs/asistencias/" local="128503348791875000" remote="128503348790000000" />
<file name="edita_no_laborable.php" server="C:/Program Files/Apache Software Foundation/Apache2.2/htdocs/asistencias/" local="128503348792187500" remote="128503348790000000" />
<file name="edita_tipo_justificacion.php" server="C:/Program Files/Apache Software Foundation/Apache2.2/htdocs/asistencias/" local="128503348792500000" remote="128503348790000000" />
<file name="inserta_categoria.php" server="C:/Program Files/Apache Software Foundation/Apache2.2/htdocs/asistencias/" local="128503348792812500" remote="128503348790000000" />
<file name="inserta_justificacion.php" server="C:/Program Files/Apache Software Foundation/Apache2.2/htdocs/asistencias/" local="128503348793281250" remote="128503348790000000" />
<file name="inserta_no_laborable.php" server="C:/Program Files/Apache Software Foundation/Apache2.2/htdocs/asistencias/" local="128503348794218750" remote="128503348790000000" />
<file name="inserta_permiso.php" server="C:/Program Files/Apache Software Foundation/Apache2.2/htdocs/asistencias/" local="128509402624062500" remote="128509402620000000" />
<file name="inserta_registros.php" server="C:/Program Files/Apache Software Foundation/Apache2.2/htdocs/asistencias/" local="128503348795781250" remote="128503348790000000" />
<file name="inserta_tipo_justificacion.php" server="C:/Program Files/Apache Software Foundation/Apache2.2/htdocs/asistencias/" local="128503348797968750" remote="128503348790000000" />
<file name="inserta_vacaciones.php" server="C:/Program Files/Apache Software Foundation/Apache2.2/htdocs/asistencias/" local="128517864144218750" remote="128517864140000000" />
<file name="edita_categoria.php" server="C:/Program Files/AppServ/www/intranet/" local="128503348800000000" remote="128503348800000000" />
<file name="edita_no_laborable.php" server="C:/Program Files/AppServ/www/intranet/" local="128503348800000000" remote="128503348800000000" />
<file name="edita_tipo_justificacion.php" server="C:/Program Files/AppServ/www/intranet/" local="128503348800000000" remote="128503348800000000" />
<file name="inserta_categoria.php" server="C:/Program Files/AppServ/www/intranet/" local="128503348800000000" remote="128503348800000000" />
<file name="inserta_justificacion.php" server="C:/Program Files/AppServ/www/intranet/" local="128517245220000000" remote="128517245220000000" />
<file name="inserta_no_laborable.php" server="C:/Program Files/AppServ/www/intranet/" local="128503348800000000" remote="128503348800000000" />
<file name="inserta_permiso.php" server="C:/Program Files/AppServ/www/intranet/" local="128509402640000000" remote="128509402640000000" />
<file name="inserta_registros.php" server="C:/Program Files/AppServ/www/intranet/" local="128517245220000000" remote="128517245220000000" />
<file name="inserta_tipo_justificacion.php" server="C:/Program Files/AppServ/www/intranet/" local="128503348800000000" remote="128503348800000000" />
<file name="inserta_vacaciones.php" server="C:/Program Files/AppServ/www/intranet/" local="128517864160000000" remote="128517864160000000" />
<file name="edita_categoria.php" server="C:/Program Files/Apache Software Foundation/Apache2.2/htdocs/intranet/" local="128660480640000000" remote="128660480640000000" />
<file name="edita_no_laborable.php" server="C:/Program Files/Apache Software Foundation/Apache2.2/htdocs/intranet/" local="128660480610000000" remote="128660480610000000" />
<file name="edita_tipo_justificacion.php" server="C:/Program Files/Apache Software Foundation/Apache2.2/htdocs/intranet/" local="128660480570000000" remote="128660480570000000" />
<file name="inserta_categoria.php" server="C:/Program Files/Apache Software Foundation/Apache2.2/htdocs/intranet/" local="128660480520000000" remote="128660480520000000" />
<file name="inserta_justificacion.php" server="C:/Program Files/Apache Software Foundation/Apache2.2/htdocs/intranet/" local="128732269330156250" remote="128732269330000000" />
<file name="inserta_no_laborable.php" server="C:/Program Files/Apache Software Foundation/Apache2.2/htdocs/intranet/" local="128660480440000000" remote="128660480440000000" />
<file name="inserta_permiso.php" server="C:/Program Files/Apache Software Foundation/Apache2.2/htdocs/intranet/" local="128660480410000000" remote="128660480410000000" />
<file name="inserta_registros.php" server="C:/Program Files/Apache Software Foundation/Apache2.2/htdocs/intranet/" local="128661384480000000" remote="128661384480000000" />
<file name="inserta_tipo_justificacion.php" server="C:/Program Files/Apache Software Foundation/Apache2.2/htdocs/intranet/" local="128660480280000000" remote="128660480280000000" />
<file name="inserta_vacaciones.php" server="C:/Program Files/Apache Software Foundation/Apache2.2/htdocs/intranet/" local="128763321944843750" remote="128763321940000000" />
<file name="index.php" server="C:/Program Files/Apache Software Foundation/Apache2.2/htdocs/intranet/" local="128668327040000000" remote="128668327040000000" />
<file name="login.php" server="C:/Program Files/Apache Software Foundation/Apache2.2/htdocs/intranet/" local="128668327040000000" remote="128668327040000000" />
<file name="inserta_solicitud_vacacion.php" server="C:/Program Files/Apache Software Foundation/Apache2.2/htdocs/intranet/" local="128702028690000000" remote="128702028690000000" />
</dwsync>